{
  "id": "bulmaca-65",
  "title": "Bulmaca 65",
  "rows": 12,
  "cols": 9,
  "clues": [
    {
      "text": "Kendi, asıl",
      "answer": "ÖZ",
      "row": 0,
      "col": 0,
      "arrow": "down-right"
    },
    {
      "text": "İran'ın başkenti",
      "answer": "TAHRAN",
      "row": 0,
      "col": 3,
      "arrow": "down-right"
    },
    {
      "text": "İkiden sonra gelen sayı",
      "answer": "ÜÇ",
      "row": 2,
      "col": 0,
      "arrow": "right"
    },
    {
      "text": "Bir seslenme sözü",
      "answer": "YA",
      "row": 2,
      "col": 3,
      "arrow": "right"
    },
    {
      "text": "Lantan'ın simgesi",
      "answer": "LA",
      "row": 2,
      "col": 6,
      "arrow": "right"
    },
    {
      "text": "İri taneli bezelye",
      "answer": "ARAKA",
      "row": 2,
      "col": 0,
      "arrow": "down-right"
    },
    {
      "text": "Zamanın çok kısa parçası",
      "answer": "AN",
      "row": 3,
      "col": 6,
      "arrow": "right"
    },
    {
      "text": "Girişken, çevik",
      "answer": "ATAK",
      "row": 4,
      "col": 0,
      "arrow": "right"
    },
    {
      "text": "İğneyle yapılan ince süs işi",
      "answer": "OYA",
      "row": 4,
      "col": 5,
      "arrow": "right"
    },
    {
      "text": "Geleceği okuma işi",
      "answer": "FAL",
      "row": 5,
      "col": 0,
      "arrow": "right"
    },
    {
      "text": "Araç, avadanlık",
      "answer": "ALET",
      "row": 6,
      "col": 0,
      "arrow": "right"
    },
    {
      "text": "Baş kaldıran",
      "answer": "ASİ",
      "row": 5,
      "col": 6,
      "arrow": "down-right"
    },
    {
      "text": "Zarfla gönderilen yazı",
      "answer": "MEKTUP",
      "row": 7,
      "col": 2,
      "arrow": "right"
    },
    {
      "text": "İsim",
      "answer": "AD",
      "row": 8,
      "col": 0,
      "arrow": "right"
    },
    {
      "text": "Eski Mısır'ın güneş tanrısı",
      "answer": "RA",
      "row": 8,
      "col": 3,
      "arrow": "right"
    },
    {
      "text": "Bir nota",
      "answer": "RE",
      "row": 8,
      "col": 6,
      "arrow": "right"
    },
    {
      "text": "Meydana gelen şey, hadise",
      "answer": "OLAY",
      "row": 9,
      "col": 1,
      "arrow": "right"
    },
    {
      "text": "Üye",
      "answer": "AZA",
      "row": 10,
      "col": 2,
      "arrow": "right"
    },
    {
      "text": "Çok karşıtı",
      "answer": "AZ",
      "row": 10,
      "col": 0,
      "arrow": "down-right"
    },
    {
      "text": "Bir nota",
      "answer": "Mİ",
      "row": 11,
      "col": 2,
      "arrow": "right"
    },
    {
      "text": "Kasapta satılan besin",
      "answer": "ET",
      "row": 11,
      "col": 6,
      "arrow": "right"
    },
    {
      "text": "Uzun boyunlu Afrika hayvanı",
      "answer": "ZÜRAFA",
      "row": 0,
      "col": 1,
      "arrow": "down"
    },
    {
      "text": "Belirti, emare",
      "answer": "İZ",
      "row": 9,
      "col": 1,
      "arrow": "down"
    },
    {
      "text": "Yemek yemede kullanılan çatallı araç",
      "answer": "ÇATAL",
      "row": 1,
      "col": 2,
      "arrow": "down"
    },
    {
      "text": "Bir nota",
      "answer": "DO",
      "row": 7,
      "col": 2,
      "arrow": "down"
    },
    {
      "text": "Yazı yazma aracı",
      "answer": "KALEM",
      "row": 2,
      "col": 3,
      "arrow": "down"
    },
    {
      "text": "Mikroskopta kullanılan cam",
      "answer": "LAM",
      "row": 8,
      "col": 3,
      "arrow": "down"
    },
    {
      "text": "Bacağın yere basan bölümü",
      "answer": "AYAK",
      "row": 0,
      "col": 4,
      "arrow": "down"
    },
    {
      "text": "Tartı aleti",
      "answer": "TERAZİ",
      "row": 5,
      "col": 4,
      "arrow": "down"
    },
    {
      "text": "'İşte' anlamında bir ünlem",
      "answer": "HA",
      "row": 0,
      "col": 5,
      "arrow": "down"
    },
    {
      "text": "Büyük taş kütlesi",
      "answer": "KAYA",
      "row": 6,
      "col": 5,
      "arrow": "down"
    },
    {
      "text": "Satrançta bir taş",
      "answer": "AT",
      "row": 5,
      "col": 6,
      "arrow": "down"
    },
    {
      "text": "Eğlenme, dalga geçme",
      "answer": "ALAY",
      "row": 0,
      "col": 7,
      "arrow": "down"
    },
    {
      "text": "Kale duvarı, hisar duvarı",
      "answer": "SUR",
      "row": 5,
      "col": 7,
      "arrow": "down"
    },
    {
      "text": "Emile Zola'nın bir romanı",
      "answer": "NANA",
      "row": 0,
      "col": 8,
      "arrow": "down"
    },
    {
      "text": "Hardal kokulu savaş gazı",
      "answer": "İPERİT",
      "row": 5,
      "col": 8,
      "arrow": "down"
    }
  ],
  "blocks": [
    {
      "row": 0,
      "col": 2
    },
    {
      "row": 0,
      "col": 6
    },
    {
      "row": 3,
      "col": 5
    },
    {
      "row": 5,
      "col": 5
    },
    {
      "row": 7,
      "col": 0
    },
    {
      "row": 7,
      "col": 1
    },
    {
      "row": 9,
      "col": 0
    },
    {
      "row": 9,
      "col": 6
    },
    {
      "row": 9,
      "col": 7
    },
    {
      "row": 10,
      "col": 6
    },
    {
      "row": 10,
      "col": 7
    },
    {
      "row": 11,
      "col": 5
    }
  ],
  "difficulty": "orta"
}