{
  "id": "bulmaca-156",
  "title": "Bulmaca 156",
  "rows": 10,
  "cols": 7,
  "clues": [
    {
      "text": "Gümüş balığı",
      "answer": "ATERİNA",
      "row": 0,
      "col": 0,
      "arrow": "down-right"
    },
    {
      "text": "Yeşil, küçük bitki",
      "answer": "OT",
      "row": 2,
      "col": 0,
      "arrow": "right"
    },
    {
      "text": "İçin için yanan ateş",
      "answer": "KOR",
      "row": 2,
      "col": 3,
      "arrow": "right"
    },
    {
      "text": "Hardal kokulu savaş gazı",
      "answer": "İPERİT",
      "row": 2,
      "col": 0,
      "arrow": "down-right"
    },
    {
      "text": "Beyaz, kara karşıtı",
      "answer": "AK",
      "row": 4,
      "col": 0,
      "arrow": "right"
    },
    {
      "text": "Kişi, şahıs (eski dilde)",
      "answer": "ZAT",
      "row": 4,
      "col": 3,
      "arrow": "right"
    },
    {
      "text": "Sivri son bölüm",
      "answer": "UÇ",
      "row": 4,
      "col": 0,
      "arrow": "down-right"
    },
    {
      "text": "Yanardağdan çıkan erimiş kayaç",
      "answer": "LAV",
      "row": 5,
      "col": 4,
      "arrow": "down-right"
    },
    {
      "text": "İri taneli bezelye",
      "answer": "ARAKA",
      "row": 7,
      "col": 1,
      "arrow": "right"
    },
    {
      "text": "Delikli, seyrek dokunmuş kumaş",
      "answer": "ETAMİN",
      "row": 8,
      "col": 0,
      "arrow": "right"
    },
    {
      "text": "Büyük, gösterişli ev",
      "answer": "KONAK",
      "row": 9,
      "col": 0,
      "arrow": "right"
    },
    {
      "text": "Çevrilerek oynanan oyuncak",
      "answer": "TOPAÇ",
      "row": 0,
      "col": 1,
      "arrow": "down"
    },
    {
      "text": "İlave, ulama",
      "answer": "EK",
      "row": 7,
      "col": 1,
      "arrow": "down"
    },
    {
      "text": "Belden aşağı giysi",
      "answer": "ETEK",
      "row": 0,
      "col": 2,
      "arrow": "down"
    },
    {
      "text": "Derebeyi konağı",
      "answer": "ŞATO",
      "row": 5,
      "col": 2,
      "arrow": "down"
    },
    {
      "text": "Nâzım Hikmet'in soyadı",
      "answer": "RAN",
      "row": 6,
      "col": 3,
      "arrow": "down"
    },
    {
      "text": "Üçüncü burç",
      "answer": "İKİZ",
      "row": 0,
      "col": 4,
      "arrow": "down"
    },
    {
      "text": "And Dağları'nın yük hayvanı",
      "answer": "LAMA",
      "row": 5,
      "col": 4,
      "arrow": "down"
    },
    {
      "text": "Müzik sesi işareti",
      "answer": "NOTA",
      "row": 0,
      "col": 5,
      "arrow": "down"
    },
    {
      "text": "Yüzüklerde kullanılan yarı değerli bir taş",
      "answer": "AKİK",
      "row": 5,
      "col": 5,
      "arrow": "down"
    },
    {
      "text": "Utanma duygusu",
      "answer": "AR",
      "row": 0,
      "col": 6,
      "arrow": "down"
    },
    {
      "text": "Odanın üst yüzeyi",
      "answer": "TAVAN",
      "row": 3,
      "col": 6,
      "arrow": "down"
    }
  ],
  "blocks": [
    {
      "row": 0,
      "col": 3
    },
    {
      "row": 5,
      "col": 3
    },
    {
      "row": 6,
      "col": 0
    },
    {
      "row": 6,
      "col": 1
    },
    {
      "row": 7,
      "col": 0
    },
    {
      "row": 9,
      "col": 6
    }
  ],
  "difficulty": "zor"
}